tr4d3r/__init__.py
tr4d3r/backend/__init__.py
tr4d3r/backend/dummy/__init__.py
tr4d3r/backend/dummy/market.py
tr4d3r/backend/robinhood/__init__.py
tr4d3r/backend/robinhood/asset.py
tr4d3r/backend/robinhood/market.py
tr4d3r/backend/robinhood/portfolio.py
tr4d3r/backend/robinhood/utils.py
tr4d3r/core/__init__.py
tr4d3r/core/asset.py
tr4d3r/core/market.py
tr4d3r/core/mechanism.py
tr4d3r/core/portfolio.py
tr4d3r/core/simulation.py
tr4d3r/core/trading.py
tr4d3r/core/notification/__init__.py
tr4d3r/utils/__init__.py
tr4d3r/utils/misc.py
tr4d3r/utils/random.py
tr4d3r-0.1.2.dist-info/LICENSE
tr4d3r-0.1.2.dist-info/METADATA
tr4d3r-0.1.2.dist-info/WHEEL
tr4d3r-0.1.2.dist-info/top_level.txt
tr4d3r-0.1.2.dist-info/RECORD
