Metadata-Version: 2.1
Name: tr4d3r
Version: 0.1.2
Summary: A rebalancing trade bot library. A good one.
Home-page: https://github.com/phurwicz/tr4d3r
Author: Pavel
Author-email: pavelhurwicz@gmail.com
License: UNKNOWN
Platform: UNKNOWN
Classifier: Programming Language :: Python :: 3
Classifier: Development Status :: 2 - Pre-Alpha
Classifier: License :: OSI Approved :: MIT License
Classifier: Operating System :: OS Independent
Requires-Python: >=3.6
License-File: LICENSE
Requires-Dist: robin-stocks
Requires-Dist: python-telegram-bot
Requires-Dist: numpy (>=1.14)
Requires-Dist: pandas (>=1.1.4)
Requires-Dist: deprecated
Requires-Dist: dill
Requires-Dist: rich
Requires-Dist: tqdm
Requires-Dist: wasabi
Requires-Dist: wrappy
